tqm/__init__.py
tqm/_core/__init__.py
tqm/_core/logger.py
tqm/_core/queue.py
tqm/_core/retry_policy/__init__.py
tqm/_core/retry_policy/delay_strategy.py
tqm/_core/retry_policy/factory_methods.py
tqm/_core/retry_policy/retry_policy.py
tqm/_core/settings.py
tqm/_core/shutdown.py
tqm/_core/task.py
tqm/_core/task_actions.py
tqm/_core/task_base.py
tqm/_core/task_builder.py
tqm/_core/task_callbacks.py
tqm/_core/task_executor.py
tqm/_core/task_options.py
tqm/_core/task_predicate.py
tqm/_core/task_retry.py
tqm/_core/task_runner.py
tqm/_core/task_state.py
tqm/_core/threadpool_interface.py
tqm/_main.py
tqm/_resources_rc.py
tqm/_ui/context_menu.py
tqm/_ui/debug_widget.py
tqm/_ui/font_loader.py
tqm/_ui/mixins/multi_select_mixin.py
tqm/_ui/mixins/view_mixin.py
tqm/_ui/progress_bar_delegate.py
tqm/_ui/tab_logs.py
tqm/_ui/task_item.py
tqm/_ui/toolbar.py
tqm/_ui/ui_controller.py
tqm/_ui/ui_view_model.py
tqm/demo/__init__.py
tqm/demo/demo.py
tqm/exceptions.py
tqm/theme/style.qss
tqm/typings.py
tqm/utils/__init__.py
tqm/utils/extract_fn_name.py
tqm/utils/open_file.py
tqm/utils/random_color.py
tqm/utils/thread_info.py
tqm/version.py
tqm/widgets/__init__.py
tqm/widgets/frame.py
tqm/widgets/help_widget.py
tqm/widgets/tool_button.py
tqm-0.2.1.dist-info/LICENSE.md
tqm-0.2.1.dist-info/METADATA
tqm-0.2.1.dist-info/WHEEL
tqm-0.2.1.dist-info/entry_points.txt
tqm-0.2.1.dist-info/RECORD
