Metadata-Version: 2.3
Name: tqm
Version: 0.2.1
Summary: Python-based parallel task queuing and execution framework with PySide2 GUI for efficient workflow management.
Keywords: task,queue,manager,pyside2,gui,threading,parallel,vfx
Author: virgilsisoe
Author-email: 28490646+sisoe24@users.noreply.github.com
Requires-Python: >=3.7.7,<3.11
Classifier: Development Status :: 4 - Beta
Classifier: Intended Audience :: Developers
Classifier: License :: OSI Approved :: MIT License
Classifier: Operating System :: OS Independent
Classifier: Programming Language :: Python :: 3
Classifier: Programming Language :: Python :: 3.8
Classifier: Programming Language :: Python :: 3.9
Classifier: Programming Language :: Python :: 3.10
Classifier: Programming Language :: Python :: 3.11
Classifier: Programming Language :: Python :: 3.7
Classifier: Topic :: Desktop Environment :: Window Managers
Classifier: Topic :: Software Development :: Libraries :: Python Modules
Classifier: Topic :: System :: Monitoring
Requires-Dist: pyside2 (>=5.15.2.1,<6.0.0.0)
Requires-Dist: pytest (>=7.4.3,<8.0.0)
Project-URL: Documentation, https://github.com/sisoe24/tqm#readme
Project-URL: Homepage, https://github.com/sisoe24/tqm
Project-URL: Repository, https://github.com/sisoe24/tqm
